xymass/2body.py
xymass/__init__.py
xymass/get_solar_spec.py
xymass/main.py
xymass/orbit_animation.py
xymass/sampler.py
xymass/test.py
xymass-1.9.0.dist-info/LICENSE
xymass-1.9.0.dist-info/METADATA
xymass-1.9.0.dist-info/WHEEL
xymass-1.9.0.dist-info/top_level.txt
xymass-1.9.0.dist-info/RECORD
