Metadata-Version: 2.1
Name: xymass
Version: 1.9.0
Summary: package to generate random samples of 2D position and mass from common stellar density and IMF models, including binary companions
Author-email: "Matthew G. Walker" <mgwalker@cmu.edu>
Project-URL: Homepage, https://github.com/mgwalkergit/xymass
Project-URL: Issues, https://github.com/mgwalkergit/xymass/issues
Classifier: Programming Language :: Python :: 3
Classifier: License :: OSI Approved :: MIT License
Classifier: Operating System :: OS Independent
Requires-Python: >=3.8
License-File: LICENSE
Requires-Dist: numpy
Requires-Dist: scipy
Requires-Dist: astropy
Requires-Dist: matplotlib
